 [
  {
    "numb": 1,
    "type": "Multiple Choices",
    "question": "What is the primary function of a keyboard?",
    "answer": "B) To enter characters into a computer",
    "options": [
      "A) To display images",
      "B) To enter characters into a computer",
      "C) To print documents",
      "D) To store data"
    ]
  },
  {
    "numb": 2,
    "type": "Multiple Choices",
    "question": "Which of the following is a type of keyboard used in mobile devices?",
    "answer": "C) On-screen keyboard",
    "options": [
      "A) Mechanical keyboard",
      "B) Ergonomic keyboard",
      "C) On-screen keyboard",
      "D) Membrane keyboard"
    ]
  },
  {
    "numb": 3,
    "type": "Multiple Choices",
    "question": "What is the main purpose of a mouse?",
    "answer": "B) To point and select objects on the screen",
    "options": [
      "A) To type text",
      "B) To point and select objects on the screen",
      "C) To scan documents",
      "D) To print images"
    ]
  },
  {
    "numb": 4,
    "type": "Multiple Choices",
    "question": "Which type of mouse tracks movements using light?",
    "answer": "B) Optical mouse",
    "options": [
      "A) Mechanical mouse",
      "B) Optical mouse",
      "C) Ball mouse",
      "D) Trackball mouse"
    ]
  },
  {
    "numb": 5,
    "type": "Multiple Choices",
    "question": "What is a stylus used for?",
    "answer": "A) Drawing or writing on a screen",
    "options": [
      "A) Drawing or writing on a screen",
      "B) Printing documents",
      "C) Capturing audio input",
      "D) Storing digital data"
    ]
  },
  {
    "numb": 6,
    "type": "Multiple Choices",
    "question": "Which device is used to convert printed text and images into digital form?",
    "answer": "B) Scanner",
    "options": [
      "A) Printer",
      "B) Scanner",
      "C) Monitor",
      "D) Keyboard"
    ]
  },
  {
    "numb": 7,
    "type": "Multiple Choices",
    "question": "What is the function of an Optical Mark Reader (OMR)?",
    "answer": "C) To tally exams and questionnaires",
    "options": [
      "A) To read barcodes",
      "B) To scan images",
      "C) To tally exams and questionnaires",
      "D) To capture biometric data"
    ]
  },
  {
    "numb": 8,
    "type": "Multiple Choices",
    "question": "Which of the following technologies is used by RFID readers?",
    "answer": "B) Radio frequency identification",
    "options": [
      "A) Barcode scanning",
      "B) Radio frequency identification",
      "C) Optical character recognition",
      "D) Magnetic ink character recognition"
    ]
  },
  {
    "numb": 9,
    "type": "Multiple Choices",
    "question": "What is a primary feature of a digital camera?",
    "answer": "B) Takes pictures and records them as digital images",
    "options": [
      "A) Prints photos directly",
      "B) Takes pictures and records them as digital images",
      "C) Scans documents into digital form",
      "D) Outputs audio data"
    ]
  },
  {
    "numb": 10,
    "type": "Multiple Choices",
    "question": "What is the quality of a digital camera measured in?",
    "answer": "B) Megapixels",
    "options": [
      "A) Gigabytes",
      "B) Megapixels",
      "C) Kilobytes",
      "D) Lumens"
    ]
  },
  {
    "numb": 11,
    "type": "Multiple Choices",
    "question": "Which of the following is a characteristic of a display device?",
    "answer": "B) Displays visual output on a screen",
    "options": [
      "A) Outputs audio",
      "B) Displays visual output on a screen",
      "C) Scans documents",
      "D) Captures digital images"
    ]
  },
  {
    "numb": 12,
    "type": "Multiple Choices",
    "question": "What is the primary difference between CRT and flat-panel displays?",
    "answer": "C) Flat-panel displays use less power and take up less space",
    "options": [
      "A) Flat-panel displays are bulkier",
      "B) CRT displays are smaller",
      "C) Flat-panel displays use less power and take up less space",
      "D) CRT displays use LED technology"
    ]
  },
  {
    "numb": 13,
    "type": "Multiple Choices",
    "question": "Which of the following types of display is most commonly used in modern devices?",
    "answer": "C) Flat-panel displays",
    "options": [
      "A) Monochrome displays",
      "B) CRT displays",
      "C) Flat-panel displays",
      "D) Plasma displays"
    ]
  },
  {
    "numb": 14,
    "question": "What type of printer uses toner powder?",
    "answer": "C) Laser printer",
    "options": [
      "A) Inkjet printer",
      "B) Dot matrix printer",
      "C) Laser printer",
      "D) Thermal printer"
    ]
  },
  {
    "numb": 15,
    "type": "Multiple Choices",
    "question": "Which printing technology is used to produce multipart forms?",
    "answer": "B) Impact printing",
    "options": [
      "A) Inkjet printing",
      "B) Impact printing",
      "C) Non-impact printing",
      "D) 3D printing"
    ]
  },
  {
    "numb": 16,
    "type": "Multiple Choices",
    "question": "What does dpi stand for in printing?",
    "answer": "A) Dots per inch",
    "options": [
      "A) Dots per inch",
      "B) Data per input",
      "C) Depth per inch",
      "D) Digital printing index"
    ]
  },
  {
    "numb": 17,
    "type": "Multiple Choices",
    "question": "Which device is used to input voice data into a computer?",
    "answer": "B) Microphone",
    "options": [
      "A) Monitor",
      "B) Microphone",
      "C) Printer",
      "D) Keyboard"
    ]
  },
  {
    "numb": 18,
    "type": "Multiple Choices",
    "question": "What is the primary use of a speech recognition system?",
    "answer": "B) To recognize and convert spoken words into digital text",
    "options": [
      "A) To output sound",
      "B) To recognize and convert spoken words into digital text",
      "C) To print text",
      "D) To display images on the screen"
    ]
  },
  {
    "numb": 19,
    "type": "Multiple Choices",
    "question": "Which of the following is an audio output device?",
    "answer": "B) Speaker",
    "options": [
      "A) Monitor",
      "B) Speaker",
      "C) Scanner",
      "D) Keyboard"
    ]
  },
  {
    "numb": 20,
    "type": "Multiple Choices",
    "question": "What is a touch screen?",
    "answer": "B) A display device that allows input by touching the screen",
    "options": [
      "A) A device used to scan images",
      "B) A display device that allows input by touching the screen",
      "C) A device that captures audio input",
      "D) A printer that uses touch input"
    ]
  },
  {
    "numb": 21,
    "type": "Multiple Choices",
    "question": "Which device is typically used in gaming and allows for full-body input?",
    "answer": "C) Perceptual computing system",
    "options": [
      "A) Trackball",
      "B) Joystick",
      "C) Perceptual computing system",
      "D) Barcode reader"
    ]
  },
  {
    "numb": 22,
    "type": "Multiple Choices",
    "question": "What is an example of a biometric reader?",
    "answer": "B) A device that captures fingerprint or voice data",
    "options": [
      "A) A scanner that reads printed text",
      "B) A device that captures fingerprint or voice data",
      "C) A pen-like device used to input drawings",
      "D) A mouse that tracks movement with light"
    ]
  },
  {
    "numb": 23,
    "type": "Multiple Choices",
    "question": "What technology do e-readers primarily use?",
    "answer": "C) E-paper",
    "options": [
      "A) OLED",
      "B) LCD",
      "C) E-paper",
      "D) Plasma"
    ]
  },
  {
    "numb": 24,
    "type": "Multiple Choices",
    "question": "Which of the following is considered an input device?",
    "answer": "C) Keyboard",
    "options": [
      "A) Monitor",
      "B) Printer",
      "C) Keyboard",
      "D) Speaker"
    ]
  },
  {
    "numb": 25,
    "type": "Multiple Choices",
    "question": "What does OCR stand for?",
    "answer": "C) Optical Character Recognition",
    "options": [
      "A) Optical Code Reader",
      "B) Output Control Reader",
      "C) Optical Character Recognition",
      "D) Output Character Resolution"
    ]
  },
  {
    "numb": 26,
    "type": "Multiple Choices",
    "question": "Which of these is a non-impact printer?",
    "answer": "B) Laser printer",
    "options": [
      "A) Dot matrix printer",
      "B) Laser printer",
      "C) Typewriter",
      "D) All of the above"
    ]
  },
  {
    "numb": 27,
    "type": "Multiple Choices",
    "question": "What type of scanner would be most appropriate for capturing detailed 3D models?",
    "answer": "C) 3D scanner",
    "options": [
      "A) Flatbed scanner",
      "B) Portable scanner",
      "C) 3D scanner",
      "D) Barcode scanner"
    ]
  },
  {
    "numb": 28,
    "type": "Multiple Choices",
    "question": "Which of these is NOT a characteristic of OLED displays?",
    "answer": "B) Require backlighting",
    "options": [
      "A) Use layers of organic material",
      "B) Require backlighting",
      "C) Have deep black levels",
      "D) Are used in smartphones"
    ]
  },
  {
    "numb": 29,
    "type": "Multiple Choices",
    "question": "Which technology is most suitable for immersive virtual reality experiences?",
    "answer": "B) VR headset",
    "options": [
      "A) Trackball",
      "B) VR headset",
      "C) Dot matrix printer",
      "D) Barcode scanner"
    ]
  },
  {
    "numb": 30,
    "type": "Multiple Choices",
    "question": "What type of output is produced by a projector?",
    "answer": "C) Visual display",
    "options": [
      "A) Audio output",
      "B) Printed output",
      "C) Visual display",
      "D) Tactile feedback"
    ]
  },
  {
    "numb": 31,
    "type": "Multiple Choices",
    "question": "Which technology is used to display images on a screen by controlling light through liquid crystals?",
    "answer": "B) LCD",
    "options": [
      "A) CRT",
      "B) LCD",
      "C) Plasma",
      "D) LED"
    ]
  },
  {
    "numb": 32,
    "type": "Multiple Choices",
    "question": "Which device would best allow a user to interact with a computer without touching the screen?",
    "answer": "B) Motion sensor",
    "options": [
      "A) Trackpad",
      "B) Motion sensor",
      "C) Keyboard",
      "D) Joystick"
    ]
  },
  {
    "numb": 33,
    "type": "Multiple Choices",
    "question": "Which of these is an example of an audio input device?",
    "answer": "A) Microphone",
    "options": [
      "A) Microphone",
      "B) Speaker",
      "C) Monitor",
      "D) Keyboard"
    ]
  },
  {
    "numb": 34,
    "type": "Multiple Choices",
    "question": "Which technology is used in barcode scanners?",
    "answer": "B) Laser scanning",
    "options": [
      "A) RFID",
      "B) Laser scanning",
      "C) OCR",
      "D) Digital imaging"
    ]
  },
  {
    "numb": 35,
    "type": "Multiple Choices",
    "question": "Which of the following is a characteristic of plasma displays?",
    "answer": "A) Use small cells containing electrically charged ionized gases",
    "options": [
      "A) Use small cells containing electrically charged ionized gases",
      "B) Require backlighting",
      "C) Are primarily used in e-readers",
      "D) Are typically smaller than 20 inches"
    ]
  },
  {
    "numb": 36,
    "type": "Multiple Choices",
    "question": "What is the main feature of a graphics tablet?",
    "answer": "A) Allows users to draw directly on the surface with a stylus",
    "options": [
      "A) Allows users to draw directly on the surface with a stylus",
      "B) Scans 3D objects",
      "C) Captures biometric data",
      "D) Prints 3D models"
    ]
  },
  {
    "numb": 37,
    "type": "Multiple Choices",
    "question": "Which device is often used in retail for quick checkout?",
    "answer": "B) Barcode scanner",
    "options": [
      "A) OCR reader",
      "B) Barcode scanner",
      "C) Document scanner",
      "D) Webcam"
    ]
  },
  {
    "numb": 38,
    "type": "Multiple Choices",
    "question": "What is the primary function of a webcam?",
    "answer": "A) Capturing video for online communication",
    "options": [
      "A) Capturing video for online communication",
      "B) Scanning documents",
      "C) Printing images",
      "D) Projecting visual displays"
    ]
  },
  {
    "numb": 39,
    "type": "Multiple Choices",
    "question": "Which of these devices is most suitable for video conferencing?",
    "answer": "A) Webcam",
    "options": [
      "A) Webcam",
      "B) Printer",
      "C) Graphics tablet",
      "D) Speaker"
    ]
  },
  {
    "numb": 40,
    "type": "Multiple Choices",
    "question": "What type of device is a touchpad?",
    "answer": "A) Input device",
    "options": [
      "A) Input device",
      "B) Output device",
      "C) Storage device",
      "D) Network device"
    ]
  },
  {
    "numb": 41,
    "type": "Multiple Choices",
    "question": "What is the main advantage of using a trackball over a traditional mouse?",
    "answer": "B) It requires less desk space and is stationary",
    "options": [
      "A) It is more portable",
      "B) It requires less desk space and is stationary",
      "C) It provides better precision",
      "D) It is wireless"
    ]
  },
  {
    "numb": 42,
    "type": "Multiple Choices",
    "question": "Which device is best suited for interactive presentations?",
    "answer": "B) Smartboard",
    "options": [
      "A) Projector",
      "B) Smartboard",
      "C) Laser printer",
      "D) Dot matrix printer"
    ]
  },
  {
    "numb": 43,
    "type": "Multiple Choices",
    "question": "What does a 3D mouse typically allow?",
    "answer": "B) Manipulation of objects in a 3D environment",
    "options": [
      "A) Regular pointing and clicking",
      "B) Manipulation of objects in a 3D environment",
      "C) Only horizontal and vertical movement",
      "D) Audio input"
    ]
  },
  {
    "numb": 44,
    "type": "Multiple Choices",
    "question": "Which device is designed for capturing video footage in various lighting conditions?",
    "answer": "C) Camcorder",
    "options": [
      "A) Digital camera",
      "B) Web camera",
      "C) Camcorder",
      "D) Document camera"
    ]
  },
  {
    "numb": 45,
    "type": "Multiple Choices",
    "question": "What is the primary use of a VR headset?",
    "answer": "B) To experience 3D virtual environments",
    "options": [
      "A) To project 2D images",
      "B) To experience 3D virtual environments",
      "C) To capture real-world images",
      "D) To scan documents"
    ]
  },
  {
    "numb": 46,
    "type": "Multiple Choices",
    "question": "Which device can be used to blend real-world and digital environments?",
    "answer": "B) Mixed reality headset",
    "options": [
      "A) VR headset",
      "B) Mixed reality headset",
      "C) Laser projector",
      "D) Digital scanner"
    ]
  },
  {
    "numb": 47,
    "type": "Multiple Choices",
    "question": "Which input device is crucial for interacting with a virtual reality environment?",
    "answer": "B) VR controller",
    "options": [
      "A) Mouse",
      "B) VR controller",
      "C) Keyboard",
      "D) Trackpad"
    ]
  },
  {
    "numb": 48,
    "type": "Multiple Choices",
    "question": "What kind of displays are typically used in smart glasses?",
    "answer": "B) OLED",
    "options": [
      "A) CRT",
      "B) OLED",
      "C) LCD",
      "D) E-ink"
    ]
  },
  {
    "numb": 49,
    "type": "Multiple Choices",
    "question": "Which technology is used for remote surgeries to control surgical tools from a distance?",
    "answer": "C) Telepresence robotics",
    "options": [
      "A) Digital writing system",
      "B) Augmented reality",
      "C) Telepresence robotics",
      "D) Barcode scanner"
    ]
  },
  {
    "numb": 50,
    "type": "Multiple Choices",
    "question": "What does LIDAR technology primarily measure?",
    "answer": "B) Light reflection to measure distances",
    "options": [
      "A) Audio frequency",
      "B) Light reflection to measure distances",
      "C) Temperature variations",
      "D) Magnetic fields"
    ]
  }
]